odoo/addons/mangono_migration/.gitlab-ci.yml
odoo/addons/mangono_migration/__init__.py
odoo/addons/mangono_migration/__manifest__.py
odoo/addons/mangono_migration/auto_load.py
odoo/addons/mangono_migration/documentation.adoc
odoo/addons/mangono_migration/hooks.py
odoo/addons/mangono_migration/mangono_migration.py
mangono_odoo_migration-1.1.2.dist-info/METADATA
mangono_odoo_migration-1.1.2.dist-info/WHEEL
mangono_odoo_migration-1.1.2.dist-info/entry_points.txt
mangono_odoo_migration-1.1.2.dist-info/RECORD
