Metadata-Version: 2.4
Name: mangono-odoo-migration
Version: 1.1.2
Summary: Server wide module to perform update script before/after installation
Requires-Python: >=3.8.19
